chainbase/__init__.py
chainbase-0.0.3.dist-info/METADATA
chainbase-0.0.3.dist-info/WHEEL
chainbase-0.0.3.dist-info/RECORD
