Metadata-Version: 2.1
Name: chainbase
Version: 0.0.3
Summary: Chainbase is a library for instantly creating langchain-based APIs with autoconfiguration for proprietary data.
License: MIT
Author: Eric Robinson
Requires-Python: >=3.11,<3.12
Classifier: License :: OSI Approved :: MIT License
Classifier: Programming Language :: Python :: 3
Classifier: Programming Language :: Python :: 3.11
Requires-Dist: chainbase-lib (==0.0.3)
